pyris/__init__.py
pyris/address.py
pyris/config.py
pyris/api/__init__.py
pyris/api/app.py
pyris/api/extract.py
pyris/api/insee.py
pyris/api/run.py
pyris/api/wsgi.py
pyris/api/queries/complete_iris.sql
pyris/api/queries/coordinate.sql
pyris/api/queries/iris.sql
pyris/api/queries/iris_activite.sql
pyris/api/queries/iris_activite_age.sql
pyris/api/queries/iris_activite_secteur.sql
pyris/api/queries/iris_activite_sex.sql
pyris/api/queries/iris_by_city_code.sql
pyris/api/queries/iris_logement.sql
pyris/api/queries/iris_logement_area.sql
pyris/api/queries/iris_logement_room.sql
pyris/api/queries/iris_logement_year.sql
pyris/api/queries/iris_population.sql
pyris/api/queries/iris_population_age.sql
pyris/api/queries/iris_population_sex.sql
pyris/api/static/iris.js
pyris/api/static/map.js
pyris/api/static/bower/bootstrap/dist/css/bootstrap-theme.css
pyris/api/static/bower/bootstrap/dist/css/bootstrap-theme.min.css
pyris/api/static/bower/bootstrap/dist/css/bootstrap.css
pyris/api/static/bower/bootstrap/dist/css/bootstrap.min.css
pyris/api/static/bower/bootstrap/dist/fonts/glyphicons-halflings-regular.eot
pyris/api/static/bower/bootstrap/dist/fonts/glyphicons-halflings-regular.svg
pyris/api/static/bower/bootstrap/dist/fonts/glyphicons-halflings-regular.ttf
pyris/api/static/bower/bootstrap/dist/fonts/glyphicons-halflings-regular.woff
pyris/api/static/bower/bootstrap/dist/fonts/glyphicons-halflings-regular.woff2
pyris/api/static/bower/bootstrap/dist/js/bootstrap.js
pyris/api/static/bower/bootstrap/dist/js/bootstrap.min.js
pyris/api/static/bower/bootstrap/dist/js/npm.js
pyris/api/static/bower/bootstrap3-typeahead/bootstrap3-typeahead.js
pyris/api/static/bower/highcharts/highcharts.js
pyris/api/static/bower/jquery/dist/jquery.js
pyris/api/static/bower/leaflet/dist/leaflet-src.js
pyris/api/static/bower/leaflet/dist/leaflet-src.js.map
pyris/api/static/bower/leaflet/dist/leaflet.css
pyris/api/static/bower/leaflet/dist/leaflet.js
pyris/api/static/bower/leaflet/dist/leaflet.js.map
pyris-0.7.1.dist-info/LICENSE
pyris-0.7.1.dist-info/METADATA
pyris-0.7.1.dist-info/WHEEL
pyris-0.7.1.dist-info/top_level.txt
pyris-0.7.1.dist-info/RECORD
