Metadata-Version: 2.1
Name: pyris
Version: 0.7.1
Summary: INSEE/IRIS geolocalization
Home-page: https://gitlab.com/Oslandia/pyris
Author: Damien Garaud
Author-email: damien.garaud@gmail.com
License: BSD
Platform: UNKNOWN
Classifier: Development Status :: 3 - Alpha
Classifier: Environment :: Web Environment
Classifier: Intended Audience :: Developers
Classifier: Operating System :: OS Independent
Classifier: Programming Language :: Python
Classifier: Programming Language :: Python :: 3.6
Classifier: Programming Language :: Python :: 3.7
Classifier: Programming Language :: Python :: 3.8
Requires-Dist: Flask (==1.1.2)
Requires-Dist: flask-restplus (==0.13.0)
Requires-Dist: Werkzeug (==0.16.1)
Requires-Dist: psycopg2-binary
Requires-Dist: pyaml
Requires-Dist: slumber
Requires-Dist: gunicorn (==19.9)
Provides-Extra: dev
Requires-Dist: pytest ; extra == 'dev'
Requires-Dist: pytest-sugar ; extra == 'dev'
Requires-Dist: ipython ; extra == 'dev'
Requires-Dist: ipdb ; extra == 'dev'
